src/__init__.py
src/graph.py
graphutils-0.1.dist-info/METADATA
graphutils-0.1.dist-info/WHEEL
graphutils-0.1.dist-info/top_level.txt
graphutils-0.1.dist-info/RECORD
